setup.cfg
setup.py
tg/__init__.py
tg.ext.silverplate.egg-info/PKG-INFO
tg.ext.silverplate.egg-info/SOURCES.txt
tg.ext.silverplate.egg-info/dependency_links.txt
tg.ext.silverplate.egg-info/entry_points.txt
tg.ext.silverplate.egg-info/namespace_packages.txt
tg.ext.silverplate.egg-info/top_level.txt
tg.ext.silverplate.egg-info/zip-safe
tg/ext/__init__.py
tg/ext/silverplate/__init__.py
tg/ext/silverplate/config.py
tg/ext/silverplate/controller.py
tg/ext/silverplate/widgets.py
tg/ext/silverplate/templates/__init__.py
tg/ext/silverplate/templates/edit.html
tg/ext/silverplate/templates/footer.html
tg/ext/silverplate/templates/groups.html
tg/ext/silverplate/templates/header.html
tg/ext/silverplate/templates/index.html
tg/ext/silverplate/templates/master.html
tg/ext/silverplate/templates/permissions.html
tg/ext/silverplate/templates/profile.html
tg/ext/silverplate/templates/registration.html
tg/ext/silverplate/templates/sidebars.html
tg/ext/silverplate/templates/tw_resources.html
tg/ext/silverplate/templates/users.html