Metadata-Version: 1.0
Name: tg.ext.silverplate
Version: 0.1rc3-r43
Summary: TurboGears Registration and Administration module
Home-page: http://code.google.com/p/tgtools/
Author: Christopher Perkins
Author-email: chris@percious.com
License: MIT
Keywords: TurboGears dbsprockets silverplate
Platform: UNKNOWN
